ocv_utils/__init__.py
ocv_utils/image_io.py
ocv_utils/video_reader.py
ocv_utils/video_writer.py
ocv_utils/window.py
ocv_utils/ops/__init__.py
ocv_utils/ops/img_concatenating.py
ocv_utils-0.0.2.dist-info/LICENSE
ocv_utils-0.0.2.dist-info/METADATA
ocv_utils-0.0.2.dist-info/WHEEL
ocv_utils-0.0.2.dist-info/top_level.txt
ocv_utils-0.0.2.dist-info/RECORD
