Metadata-Version: 2.1
Name: ocv_utils
Version: 0.0.2
Summary: Simplifies OpenCV functionalities for image and video i/o and debug-windows.
Home-page: https://github.com/alpe6825/ocv_utils
Author: Alpe6825
Classifier: Programming Language :: Python :: 3
Classifier: License :: OSI Approved :: MIT License
Classifier: Operating System :: OS Independent
Requires-Python: >=3.6
License-File: LICENSE
Requires-Dist: opencv-python>=4.0
